jwt_helper/__init__.py
jwt_helper/_issuer.py
jwt_helper/_jwtencoder.py
jwt_helper/_jwtvalidator.py
jwt_helper/_load_key_from_disk.py
jwt_helper/_signmethods.py
jwt_helper/_version.py
jwt_helper-0.0.11.dist-info/LICENSE
jwt_helper-0.0.11.dist-info/METADATA
jwt_helper-0.0.11.dist-info/WHEEL
jwt_helper-0.0.11.dist-info/top_level.txt
jwt_helper-0.0.11.dist-info/RECORD
