Metadata-Version: 2.1
Name: jwt-helper
Version: 0.0.11
Summary: A wrapper around pyjwt
Home-page: https://github.com/bad-microservices/jwt_helper
Author: Ole Hannemann
Author-email: cerberus885@gmail.com
License: MIT
Keywords: JWT
Classifier: Programming Language :: Python :: 3.0
Classifier: Programming Language :: Python :: 3.9
Classifier: License :: OSI Approved :: MIT License
Classifier: Development Status :: 3 - Alpha
Classifier: Topic :: Software Development :: Libraries :: Python Modules
Classifier: Intended Audience :: Developers
License-File: LICENSE
Requires-Dist: setuptools (>=45.0)
Requires-Dist: pyjwt
Requires-Dist: cryptography
